localstack_stripe/__init__.py
localstack_stripe/extension.py
localstack_stripe/localstripe.py
localstack_extension_stripe-0.1.0.dist-info/LICENSE
localstack_extension_stripe-0.1.0.dist-info/METADATA
localstack_extension_stripe-0.1.0.dist-info/WHEEL
localstack_extension_stripe-0.1.0.dist-info/entry_points.txt
localstack_extension_stripe-0.1.0.dist-info/top_level.txt
localstack_extension_stripe-0.1.0.dist-info/RECORD
